readme_gen/__init__.py
readme_gen/generator.py
readme_gen-0.1.dist-info/METADATA
readme_gen-0.1.dist-info/WHEEL
readme_gen-0.1.dist-info/top_level.txt
readme_gen-0.1.dist-info/RECORD
