Metadata-Version: 2.1
Name: readme_gen
Version: 0.1
Summary: A simple package to generate README files for projects automatically.
Home-page: https://github.com/Eshaniqbal/Readme_gen-Package
Author: Eshan Iqbal
Author-email: mireshan321@gmail.com
Classifier: Programming Language :: Python :: 3
Classifier: License :: OSI Approved :: MIT License
Classifier: Operating System :: OS Independent
